odoo8_addon_hr_expense_line_supplier-8.0.1.0.0.99.dev7-py2.7-nspkg.pth
odoo8_addon_hr_expense_line_supplier-8.0.1.0.0.99.dev7.dist-info/METADATA
odoo8_addon_hr_expense_line_supplier-8.0.1.0.0.99.dev7.dist-info/RECORD
odoo8_addon_hr_expense_line_supplier-8.0.1.0.0.99.dev7.dist-info/WHEEL
odoo8_addon_hr_expense_line_supplier-8.0.1.0.0.99.dev7.dist-info/namespace_packages.txt
odoo8_addon_hr_expense_line_supplier-8.0.1.0.0.99.dev7.dist-info/top_level.txt
odoo_addons/hr_expense_line_supplier/README.rst
odoo_addons/hr_expense_line_supplier/__init__.py
odoo_addons/hr_expense_line_supplier/__openerp__.py
odoo_addons/hr_expense_line_supplier/demo/hr_expense_line.xml
odoo_addons/hr_expense_line_supplier/i18n/fr.po
odoo_addons/hr_expense_line_supplier/i18n/fr_CA.po
odoo_addons/hr_expense_line_supplier/i18n/hr_expense_line_supplier.pot
odoo_addons/hr_expense_line_supplier/i18n/nb_NO.po
odoo_addons/hr_expense_line_supplier/i18n/sl.po
odoo_addons/hr_expense_line_supplier/models/__init__.py
odoo_addons/hr_expense_line_supplier/models/hr_expense_line.py
odoo_addons/hr_expense_line_supplier/static/description/icon.png
odoo_addons/hr_expense_line_supplier/views/hr_expense_line.xml
